{
  "更新时间": "2025-12-18T04:01:21.688514+00:00",
  "数据": {
    "财联社": {
      "名称": "财联社-全球快讯",
      "状态": "正常",
      "数据": [
        {
          "标题": "",
          "内容": "财联社12月18日电，泰国央行总裁称，做好了进一步降息的准备，货币政策空间有限，利率过低会影响储蓄。",
          "发布日期": "2025-12-18",
          "发布时间": "11:12:31"
        },
        {
          "标题": "沪深两市成交额突破1万亿 较昨日此时放量近200亿",
          "内容": "【沪深两市成交额突破1万亿 较昨日此时放量近200亿】财联社12月18日电，据财联社盯盘数据显示，沪深两市成交额连续第141个交易日突破1万亿，较昨日此时放量近200亿，预计全天成交金额约1.7万亿。",
          "发布日期": "2025-12-18",
          "发布时间": "11:16:42"
        },
        {
          "标题": "中国光伏行业协会：主产业链环节盈利能力逐渐改善 企业亏损持续收窄",
          "内容": "【中国光伏行业协会：主产业链环节盈利能力逐渐改善 企业亏损持续收窄】财联社12月18日电，在今日进行的2025光伏行业年度大会上，中国光伏行业协会名誉理事长王勃华在主旨报告中表示，今年以来，光伏主产业链环节盈利能力逐渐改善，企业亏损持续收窄，2025年前三季度亏损达310.39亿元，其中第三季度亏损64.22亿元，相比第二季度亏损减少56.18亿元，收窄约46.7%。（财联社记者 刘梦然）",
          "发布日期": "2025-12-18",
          "发布时间": "11:18:14"
        },
        {
          "标题": "福建舰通过台湾海峡台军紧盯 还派F-16“偷拍”",
          "内容": "【福建舰通过台湾海峡台军紧盯 还派F-16“偷拍”】财联社12月18日电，据环球时报，解放军第三艘航母福建舰正式入列后的动向备受关注。据台湾中时新闻网17日报道，台防务部门当天早上公布福建舰通过台湾海峡的画面，并称福建舰16日航经台湾海峡，台军“严密监控”。台媒称，这是福建舰入列后首度航经台湾海峡，这一路线选择具有高度政治与军事象征意义。台军方称，17日8时30分起，陆续侦获解放军歼-10、轰-6K、空警-500等各型主、辅战机及无人机计23架次出海，其中14架次逾越所谓“海峡中线”及其延伸线，进入台湾北部、中部、西南及东部空域，配合解放军军舰进行“联合战备警巡”。台媒称，福建舰通过台湾海峡的影像由台军F-16战机用侦察吊舱拍摄。",
          "发布日期": "2025-12-18",
          "发布时间": "11:19:14"
        },
        {
          "标题": "五粮液：2026年计划新增专卖店80家 坚决遏制低价抛售",
          "内容": "【五粮液：2026年计划新增专卖店80家 坚决遏制低价抛售】财联社12月18日电，五粮液今日举行经销商大会。会上，公司管理层表示，第八代五粮液坚持量价平衡原则，为经销商切实减压。公司将坚决遏制低价抛售，取消跨省开箱、跨渠道窜货等不合规、低质量的销售奖励，坚决终止违规商家合作。2026年，五粮液计划新增专卖店80家、优化一批低质量专卖店，总量保持在1700家左右；新增集合店300家、文化体验店10家。（财联社记者 朱万平）",
          "发布日期": "2025-12-18",
          "发布时间": "11:19:19"
        },
        {
          "标题": "Momenta获Grab战略投资",
          "内容": "【Momenta获Grab战略投资】财联社12月18日电，记者获悉，Momenta获东南亚出行及生活服务平台Grab战略投资，并达成战略合作。基于此合作，Momenta与Grab将探索将L4级自动驾驶能力直接集成于量产车型中，形成了无需后期昂贵改装即可投入运营的一体化解决方案，并进入东南亚市场。（财联社记者 刘阳）",
          "发布日期": "2025-12-18",
          "发布时间": "11:20:27"
        },
        {
          "标题": "海南自贸港启动全岛封关 洋浦港口岸第一批“零关税”货物顺利通关",
          "内容": "【海南自贸港启动全岛封关 洋浦港口岸第一批“零关税”货物顺利通关】财联社12月18日电，今日上午，伴随着悠长响亮的鸣笛声，一艘装载着石化原辅料的船舶抵达洋浦港。这是海南自由贸易港正式启动全岛封关后洋浦港口岸第一批通关的“零关税”石化原辅料，进口量为17.9万吨，货值近4亿元，较封关前在进口环节为企业节省成本近千万元。 第一批“零关税”石化原辅料顺利通关，标志着洋浦石化产业可享受原料“零关税”进口及加工增值免关税内销双重红利，为推动石化产业链往高端走、往下游走提供了坚实保障。",
          "发布日期": "2025-12-18",
          "发布时间": "11:22:03"
        },
        {
          "标题": "午评：创业板指半日跌近2% 商业航天概念集体上涨",
          "内容": "【午评：创业板指半日跌近2% 商业航天概念集体上涨】财联社12月18日电，三大指数涨跌不一，沪指拉升翻红，创业板指跌近2%。黄白线明显分化，微盘股指数涨超2%。沪深两市半日成交额1.05万亿，较上个交易日放量212亿。盘面上热点快速轮动，全市场超3600只个股上涨。从板块来看，商业航天概念再度爆发，盛洋科技2连板，顺灏股份、天银机电、中国卫星等多股涨停。大消费板块走强，零售方向领涨，中央商场、上海九百涨停。IP经济概念表现活跃，广博股份、三湘印象涨停。AI医疗概念震荡拉升，华人健康20cm涨停。下跌方面，锂电池板块回落，海科新源、宁德时代下挫。板块方面，医药商业、商业航天、等板块涨幅居前，电池、证券等板块跌幅居前。截至收盘，沪指涨0.16%，深成指跌0.85%，创业板指跌1.81%。",
          "发布日期": "2025-12-18",
          "发布时间": "11:32:25"
        },
        {
          "标题": "【大佬持仓跟踪】智能驾驶+机器人+阿里云，方案实现L2到L4多场景辅助驾驶功能，与智元和阿里云达成战略合作，这家公司布局机器人全身解决方案",
          "内容": "智能驾驶+机器人+阿里云，方案实现L2到L4多场景辅助驾驶功能，与智元和阿里云达成战略合作，布局机器人头部、胸腔、底盘、肢体总成解决方案，这家公司智驾领域产品份额国内第二。",
          "发布日期": "2025-12-18",
          "发布时间": "11:33:50"
        },
        {
          "标题": "中国光伏行业协会名誉理事长王勃华：多晶硅产量12年来首次下降",
          "内容": "【中国光伏行业协会名誉理事长王勃华：多晶硅产量12年来首次下降】财联社12月18日电，在2025光伏行业年度大会上，中国光伏行业协会名誉理事长王勃华在报告中表示，多晶硅自2013年以来产量首次同比下降，硅片自2009年以来首次同比下降。其给出的数据显示，2025年1-10月，多晶硅产量约111.3万吨，同比下降29.6%；硅片产量约567GW，同比下降6.7%。电池片产量约560GW，同比增长9.8%，光伏组件产量约514GW，同比增长13.5%。",
          "发布日期": "2025-12-18",
          "发布时间": "11:36:37"
        },
        {
          "标题": "印尼东爪哇省一火山喷发 火山灰柱高约800米",
          "内容": "【印尼东爪哇省一火山喷发 火山灰柱高约800米】财联社12月18日电，据印尼火山地质减灾中心(PVMBG)消息，当地时间2025年12月18日6时51分，印尼东爪哇省塞梅鲁火山发生喷发。火山灰柱高约800米，喷发持续时间为114秒。",
          "发布日期": "2025-12-18",
          "发布时间": "11:38:10"
        },
        {
          "标题": "中国气象局：到2035年建成自主可控、国际先进的地球系统预报体系",
          "内容": "【中国气象局：到2035年建成自主可控、国际先进的地球系统预报体系】财联社12月18日电，中国气象局今天上午举行新闻发布会，会上发布《地球系统预报发展战略（2025—2035年）》。《战略》的目标：到2035年，要建成自主可控、国际先进的地球系统预报体系。这个目标将通过两个阶段稳步推进。未来五年内，重点实现新一代预报模式的业务化运行，并建成气象人工智能模型的统一基础框架。推动各项技术的深度融合，发布第一代地球系统数字服务平台。在2030年至2035年间，全面建成统一框架的地球系统预报体系，显著提升对地球系统多尺度、多圈层相互作用的模拟和预测能力。",
          "发布日期": "2025-12-18",
          "发布时间": "11:46:51"
        },
        {
          "标题": "美光CEO：全球HBM潜在市场有望在2028年达到千亿美元",
          "内容": "【美光CEO：全球HBM潜在市场有望在2028年达到千亿美元】财联社12月18日电，美东时间周三盘后，美光公布的财报显示HBM市场需求爆棚，公司CEO桑贾伊·梅赫罗特拉（Sanjay Mehrotra）在业绩电话会上表示，预计到2028年，全球HBM总潜在市场（TAM）的复合年增长率（CAGR）约为40%，将从2025年的约350亿美元增长至2028年的约1000亿美元。这一里程碑预期将比此前展望提前两年实现。",
          "发布日期": "2025-12-18",
          "发布时间": "11:47:55"
        },
        {
          "标题": "中银证券回应APP下架：已切实采取有效措施保障整改到位",
          "内容": "【中银证券回应APP下架：已切实采取有效措施保障整改到位】财联社12月18日电，上海市通信管理局12月17日通报下架中银证券在内的38款APP，对此中银证券回应表示，公司始终高度重视用户信息保护工作，致力于为客户提供安全、可靠、放心的互联网应用使用体验。接到上海市通信管理局11月通报指出的问题后，公司迅速开展整改并按要求提交整改及自评估报告。针对APP在部分应用商城被下架问题，公司正积极与相关方沟通了解情况，力争尽快解决。我们充分尊重并虚心接受监管提出的意见建议，切实采取有效措施保障整改到位。（财联社记者 王晨）",
          "发布日期": "2025-12-18",
          "发布时间": "11:48:59"
        },
        {
          "标题": "柬埔寨内政部：柬泰冲突已致18名柬平民死亡",
          "内容": "【柬埔寨内政部：柬泰冲突已致18名柬平民死亡】财联社12月18日电，据新华社报道，柬埔寨内政部发言人杜索卡18日在新闻发布会上说，截至17日下午6时，新一轮柬泰冲突中丧生的柬埔寨平民总数已达18人，受伤人数升至78人。他说，流离失所者总数已增至14.4万个家庭，共计47.6万人，其中包括约24万名妇女和13万名儿童。柬埔寨国防部发言人马莉淑洁达当天在新闻发布会上表示，从17日午夜至18日凌晨，泰国军队持续攻击柬埔寨境内多个地点。12月7日起，柬泰边境地区再次爆发激烈冲突。双方均指责对方“先开火”。",
          "发布日期": "2025-12-18",
          "发布时间": "11:49:56"
        },
        {
          "标题": "12月18日午间涨停分析",
          "内容": "【12月18日午间涨停分析】财联社12月18日电，今日午盘全市场共53股涨停，连板股总数15只，12股封板未遂，封板率为82%（不含ST股、退市股）。焦点股方面，零售板块百大集团6连板、南京商旅9天5板，商业航天概念股顺灏股份15天8板，实控人变更的胜通能源5连板、皮阿诺4连板。",
          "发布日期": "2025-12-18",
          "发布时间": "11:49:57"
        },
        {
          "标题": "",
          "内容": "财联社12月18日电，派杰投资将美光科技目标价从200美元上调至275美元。",
          "发布日期": "2025-12-18",
          "发布时间": "11:51:27"
        },
        {
          "标题": "",
          "内容": "财联社12月18日电，台积电据悉将于明年夏天在美国亚利桑那州工厂安装3纳米制程设备。",
          "发布日期": "2025-12-18",
          "发布时间": "11:55:42"
        },
        {
          "标题": "隆基绿能李振国：呼吁行业强化自律 坚决抵制非理性竞争",
          "内容": "【隆基绿能李振国：呼吁行业强化自律 坚决抵制非理性竞争】财联社12月18日电，隆基绿能创始人、首席技术官李振国在2025光伏行业年度大会期间深入分析了当前光伏产业发展态势，并呼吁全行业强化自律、抵制非理性竞争，共同推动产业链协同、健康发展。“面对当前形势，光伏行业需要凝聚共识、齐心协力。”李振国表示，一方面，要持续强化创新引领、构建韧性协同的供应链体系，积极开拓全球市场，持续提升中国光伏品牌的国际影响力与竞争力；另一方面，呼吁产业链上下游企业加强务实合作，强化行业自律，坚决抵制非理性竞争，合力营造开放包容、规范有序、韧性高效的产业新生态，为构建新型能源体系、保障国家能源安全贡献光伏力量。 (中证金牛座)",
          "发布日期": "2025-12-18",
          "发布时间": "11:59:18"
        },
        {
          "标题": "",
          "内容": "财联社12月18日电，港股午间收盘，恒生指数跌0.44%，恒生科技指数跌1.26%。",
          "发布日期": "2025-12-18",
          "发布时间": "12:00:37"
        }
      ]
    },
    "东方财富个股新闻": {
      "名称": "东方财富-个股新闻",
      "状态": "跳过",
      "错误": "官方接口返回格式异常，已临时跳过",
      "数据": []
    },
    "东方财富最新资讯": {
      "名称": "东方财富-最新资讯",
      "状态": "跳过",
      "错误": "官方接口返回格式异常，已临时跳过",
      "数据": []
    },
    "东方财富个股热度榜": {
      "名称": "东方财富-个股热度榜",
      "状态": "正常",
      "数据": [
        {
          "当前排名": 1,
          "代码": "SH601995",
          "股票名称": "中金公司",
          "最新价": 36.65,
          "涨跌额": 1.8471600000000001,
          "涨跌幅": 5.04
        },
        {
          "当前排名": 2,
          "代码": "SH688802",
          "股票名称": "C沐曦-U",
          "最新价": 797.99,
          "涨跌额": -30.722615,
          "涨跌幅": -3.85
        },
        {
          "当前排名": 3,
          "代码": "SH601198",
          "股票名称": "东兴证券",
          "最新价": 14.44,
          "涨跌额": 1.441112,
          "涨跌幅": 9.98
        },
        {
          "当前排名": 4,
          "代码": "SH601933",
          "股票名称": "永辉超市",
          "最新价": 5.42,
          "涨跌额": 0.040108,
          "涨跌幅": 0.74
        },
        {
          "当前排名": 5,
          "代码": "SZ002837",
          "股票名称": "英维克",
          "最新价": 96.43,
          "涨跌额": 3.606482,
          "涨跌幅": 3.74
        },
        {
          "当前排名": 6,
          "代码": "SZ000592",
          "股票名称": "平潭发展",
          "最新价": 14.37,
          "涨跌额": 0.5719259999999999,
          "涨跌幅": 3.98
        },
        {
          "当前排名": 7,
          "代码": "SZ002565",
          "股票名称": "顺灏股份",
          "最新价": 16.69,
          "涨跌额": 1.672338,
          "涨跌幅": 10.02
        },
        {
          "当前排名": 8,
          "代码": "SZ000547",
          "股票名称": "航天发展",
          "最新价": 21.68,
          "涨跌额": 0.648232,
          "涨跌幅": 2.99
        },
        {
          "当前排名": 9,
          "代码": "SH600879",
          "股票名称": "航天电子",
          "最新价": 18.14,
          "涨跌额": 1.217194,
          "涨跌幅": 6.71
        },
        {
          "当前排名": 10,
          "代码": "SZ002536",
          "股票名称": "飞龙股份",
          "最新价": 30.35,
          "涨跌额": 3.035,
          "涨跌幅": 10.0
        },
        {
          "当前排名": 11,
          "代码": "SH601059",
          "股票名称": "信达证券",
          "最新价": 18.6,
          "涨跌额": 0.8463,
          "涨跌幅": 4.55
        },
        {
          "当前排名": 12,
          "代码": "SH600865",
          "股票名称": "百大集团",
          "最新价": 17.4,
          "涨跌额": 1.73826,
          "涨跌幅": 9.99
        },
        {
          "当前排名": 13,
          "代码": "SZ002149",
          "股票名称": "西部材料",
          "最新价": 34.29,
          "涨跌额": 3.4324289999999995,
          "涨跌幅": 10.01
        },
        {
          "当前排名": 14,
          "代码": "SZ002759",
          "股票名称": "天际股份",
          "最新价": 34.99,
          "涨跌额": 0.262425,
          "涨跌幅": 0.75
        },
        {
          "当前排名": 15,
          "代码": "SZ300342",
          "股票名称": "天银机电",
          "最新价": 30.2,
          "涨跌额": 6.0339599999999995,
          "涨跌幅": 19.98
        },
        {
          "当前排名": 16,
          "代码": "SH600118",
          "股票名称": "中国卫星",
          "最新价": 58.1,
          "涨跌额": 5.81,
          "涨跌幅": 10.0
        },
        {
          "当前排名": 17,
          "代码": "SH603123",
          "股票名称": "翠微股份",
          "最新价": 13.74,
          "涨跌额": -0.369606,
          "涨跌幅": -2.69
        },
        {
          "当前排名": 18,
          "代码": "SZ002703",
          "股票名称": "浙江世宝",
          "最新价": 15.92,
          "涨跌额": 1.595184,
          "涨跌幅": 10.02
        },
        {
          "当前排名": 19,
          "代码": "SZ002682",
          "股票名称": "龙洲股份",
          "最新价": 10.14,
          "涨跌额": 0.4928040000000001,
          "涨跌幅": 4.86
        },
        {
          "当前排名": 20,
          "代码": "SZ002044",
          "股票名称": "美年健康",
          "最新价": 6.02,
          "涨跌额": 0.6050099999999999,
          "涨跌幅": 10.05
        },
        {
          "当前排名": 21,
          "代码": "SH600693",
          "股票名称": "东百集团",
          "最新价": 17.28,
          "涨跌额": 0.5788800000000001,
          "涨跌幅": 3.35
        },
        {
          "当前排名": 22,
          "代码": "SZ002549",
          "股票名称": "凯美特气",
          "最新价": 22.23,
          "涨跌额": 2.2230000000000003,
          "涨跌幅": 10.0
        },
        {
          "当前排名": 23,
          "代码": "SH601366",
          "股票名称": "利群股份",
          "最新价": 6.04,
          "涨跌额": 0.605208,
          "涨跌幅": 10.02
        },
        {
          "当前排名": 24,
          "代码": "SH600151",
          "股票名称": "航天机电",
          "最新价": 19.03,
          "涨跌额": 0.9553059999999999,
          "涨跌幅": 5.02
        },
        {
          "当前排名": 25,
          "代码": "SZ001208",
          "股票名称": "华菱线缆",
          "最新价": 21.42,
          "涨跌额": 0.638316,
          "涨跌幅": 2.98
        },
        {
          "当前排名": 26,
          "代码": "SZ002792",
          "股票名称": "通宇通讯",
          "最新价": 33.69,
          "涨跌额": 2.1258389999999996,
          "涨跌幅": 6.31
        },
        {
          "当前排名": 27,
          "代码": "SZ002491",
          "股票名称": "通鼎互联",
          "最新价": 6.84,
          "涨跌额": 0.681948,
          "涨跌幅": 9.97
        },
        {
          "当前排名": 28,
          "代码": "SZ002413",
          "股票名称": "雷科防务",
          "最新价": 9.47,
          "涨跌额": 0.33145,
          "涨跌幅": 3.5
        },
        {
          "当前排名": 29,
          "代码": "SZ002639",
          "股票名称": "雪人集团",
          "最新价": 19.09,
          "涨跌额": -0.51543,
          "涨跌幅": -2.7
        },
        {
          "当前排名": 30,
          "代码": "SZ301123",
          "股票名称": "奕东电子",
          "最新价": 58.69,
          "涨跌额": 6.57328,
          "涨跌幅": 11.2
        },
        {
          "当前排名": 31,
          "代码": "SH688795",
          "股票名称": "摩尔线程-U",
          "最新价": 714.12,
          "涨跌额": -0.7141200000000001,
          "涨跌幅": -0.1
        },
        {
          "当前排名": 32,
          "代码": "SH600280",
          "股票名称": "中央商场",
          "最新价": 4.68,
          "涨跌额": 0.473616,
          "涨跌幅": 10.12
        },
        {
          "当前排名": 33,
          "代码": "SH601869",
          "股票名称": "长飞光纤",
          "最新价": 108.05,
          "涨跌额": 10.805,
          "涨跌幅": 10.0
        },
        {
          "当前排名": 34,
          "代码": "SZ001330",
          "股票名称": "博纳影业",
          "最新价": 10.73,
          "涨跌额": 0.982868,
          "涨跌幅": 9.16
        },
        {
          "当前排名": 35,
          "代码": "SZ301408",
          "股票名称": "华人健康",
          "最新价": 21.84,
          "涨跌额": 4.368,
          "涨跌幅": 20.0
        },
        {
          "当前排名": 36,
          "代码": "SZ300456",
          "股票名称": "赛微电子",
          "最新价": 64.27,
          "涨跌额": 3.6248279999999995,
          "涨跌幅": 5.64
        },
        {
          "当前排名": 37,
          "代码": "SZ001325",
          "股票名称": "N元创",
          "最新价": 70.99,
          "涨跌额": 132.630617,
          "涨跌幅": 186.83
        },
        {
          "当前排名": 38,
          "代码": "SH603122",
          "股票名称": "合富中国",
          "最新价": 28.64,
          "涨跌额": 1.242976,
          "涨跌幅": 4.34
        },
        {
          "当前排名": 39,
          "代码": "SZ002788",
          "股票名称": "鹭燕医药",
          "最新价": 13.9,
          "涨跌额": 1.38583,
          "涨跌幅": 9.97
        },
        {
          "当前排名": 40,
          "代码": "SZ000546",
          "股票名称": "金圆股份",
          "最新价": 7.14,
          "涨跌额": 0.412692,
          "涨跌幅": 5.78
        },
        {
          "当前排名": 41,
          "代码": "SH600250",
          "股票名称": "南京商旅",
          "最新价": 14.62,
          "涨跌额": 1.4634619999999998,
          "涨跌幅": 10.01
        },
        {
          "当前排名": 42,
          "代码": "SH600343",
          "股票名称": "航天动力",
          "最新价": 37.84,
          "涨跌额": 1.7141520000000003,
          "涨跌幅": 4.53
        },
        {
          "当前排名": 43,
          "代码": "SZ300710",
          "股票名称": "万隆光电",
          "最新价": 30.88,
          "涨跌额": 6.182175999999999,
          "涨跌幅": 20.02
        },
        {
          "当前排名": 44,
          "代码": "SZ001317",
          "股票名称": "三羊马",
          "最新价": 57.03,
          "涨跌额": -0.17109,
          "涨跌幅": -0.3
        },
        {
          "当前排名": 45,
          "代码": "SH600105",
          "股票名称": "永鼎股份",
          "最新价": 20.38,
          "涨跌额": 0.050949999999999995,
          "涨跌幅": 0.25
        },
        {
          "当前排名": 46,
          "代码": "SH601138",
          "股票名称": "工业富联",
          "最新价": 58.76,
          "涨跌额": -2.6206959999999997,
          "涨跌幅": -4.46
        },
        {
          "当前排名": 47,
          "代码": "SZ002281",
          "股票名称": "光迅科技",
          "最新价": 68.86,
          "涨跌额": 0.268554,
          "涨跌幅": 0.39
        },
        {
          "当前排名": 48,
          "代码": "SH601566",
          "股票名称": "九牧王",
          "最新价": 15.44,
          "涨跌额": 1.539368,
          "涨跌幅": 9.97
        },
        {
          "当前排名": 49,
          "代码": "SH600501",
          "股票名称": "航天晨光",
          "最新价": 27.58,
          "涨跌额": 0.5516,
          "涨跌幅": 2.0
        },
        {
          "当前排名": 50,
          "代码": "SZ000950",
          "股票名称": "重药控股",
          "最新价": 6.86,
          "涨跌额": 0.681884,
          "涨跌幅": 9.94
        }
      ]
    },
    "东方财富热门板块": {
      "名称": "东方财富-热门板块",
      "状态": "缺失",
      "错误": "akshare 无 stock_board_concept_name 接口",
      "数据": []
    },
    "央视新闻": {
      "名称": "央视新闻",
      "状态": "正常",
      "数据": [
        {
          "date": "20240424",
          "title": "习近平在重庆考察时强调 进一步全面深化改革开放 不断谱写中国式现代化重庆篇章",
          "content": "中共中央总书记、国家主席、中央军委主席习近平近日在重庆考察时强调，重庆要对标新时代新征程党的中心任务和党中央赋予的使命，充分发挥比较优势、后发优势，进一步全面深化改革开放，主动服务和融入新发展格局，着力推动高质量发展，奋力打造新时代西部大开发重要战略支点、内陆开放综合枢纽，在发挥“三个作用”上展现更大作为，不断谱写中国式现代化重庆篇章。4月22日至24日，习近平在中共中央政治局委员、重庆市委书记袁家军和市长胡衡华陪同下，深入物流园区、城市社区、数字化城市运行和治理中心等进行考察调研。22日下午，习近平首先考察了重庆国际物流枢纽园区。他来到西部陆海新通道重庆无水港运营调度中心，听取新通道建设情况汇报。习近平强调，物流是实体经济的“筋络”。建设西部陆海新通道，对于推动形成“陆海内外联动、东西双向互济”的对外开放格局具有重要意义。各有关方面要齐心协力，把这一标志性项目建设好、运营好，带动西部和内陆地区高水平对外开放。物流园区要积极运用先进技术，不断创新联运模式，提高科学管理水平，在建设现代物流体系中发挥更大作用。随后，习近平来到重庆铁路集装箱中心站，听取货物集散、运输路径、运营成本和效益等介绍，同货车司机、列车司机、装卸工人、场站管理人员等亲切交流，询问他们的工作强度、劳动保护、节假日休息和收入情况。习近平说，大家在物流一线，也是在对外开放一线，通过你们的辛勤劳动，很多商品跨越山海、走向世界，你们的工作很有意义。推动西部大开放、促进西部大开发，物流很重要，大家要继续努力，不断创造新的业绩，作出新的贡献。习近平还听取了重庆推动成渝地区双城经济圈建设情况汇报，参观了重庆科技创新和产业发展成果展示。习近平表示，建设成渝地区双城经济圈是党中央作出的重大战略决策。重庆、四川两地要紧密合作，不断提升发展能级，共同唱好新时代西部“双城记”。支柱产业是发展新质生产力的主阵地。重庆的制造业有自身的结构特点、有相应的优势，希望重庆牢牢抓住科技创新这个“牛鼻子”，扬优势、补短板，抓当前、谋未来，坚定不移、久久为功，奋力推动制造业高质量发展。九龙坡区谢家湾街道民主村社区是一个老小区，2022年初启动更新改造项目并纳入全国有关试点。习近平来到这里，察看小区改造和便民服务情况，听取提升基层治理效能、为基层减负情况介绍。他还走进社区食堂，同正在就餐的群众亲切交流，鼓励社区食堂实现可持续发展。习近平指出，老旧小区改造是城市更新的一个重点，也是一项民生工程，既要保留历史记忆和特色风貌，又要解决居民关切的实际问题。要总结推广这方面的成功经验，更好惠及广大社区居民。城市治理的很多工作要靠基层党组织这个战斗堡垒和社区这个平台去落实，要厘清城市社区职责事项，继续推动资源下沉、完善服务设施，强化网格化管理、信息化支撑，提高社区精细化治理、精准化服务水平。离开时，社区居民纷纷围拢过来欢送总书记。习近平对大家说，中国式现代化，民生为大。党和政府的一切工作，都是为了老百姓过上更加幸福的生活。希望各级党委和政府都能为解决民生问题投入更多的财力物力，每年办一些民生实事，不断增强人民群众的获得感幸福感安全感。23日上午，习近平考察了重庆市数字化城市运行和治理中心，听取当地加快城市数字化转型、探索超大城市治理新路等情况汇报，观看系统应用演示。习近平指出，治理体系和治理能力现代化是中国式现代化的应有之义。强化数字赋能、推进城市治理现代化，要科学规划建设大数据平台和网络系统，强化联合指挥和各方协同，切实提高执行力。城市治理涉及方方面面，首要的是以“时时放心不下”的责任感，做好预案、精准管控、快速反应，有效处置各类事态，确保城市安全有序运行。希望你们不断探索，积累新的经验。24日上午，习近平听取了重庆市委和市政府工作汇报，对重庆各项工作取得的成绩给予肯定。习近平指出，重庆制造业基础较好，科教人才资源丰富，要着力构建以先进制造业为骨干的现代化产业体系。深入实施制造业重大技术改造升级和大规模设备更新工程，加快传统产业转型升级，积极培育具有国际先进水平和竞争力的战略性新兴产业。加强重大科技攻关，强化科技创新和产业创新深度融合，积极培育新业态新模式新动能，因地制宜发展新质生产力。积极推进成渝地区双城经济圈建设，更好发挥全国高质量发展的重要增长极和新的动力源作用。大力推动绿色发展，建设美丽重庆，筑牢长江上游重要生态屏障。习近平强调，重庆要以敢为人先的勇气，全面深化改革，扩大高水平对外开放。坚持和落实“两个毫不动摇”，一手抓深化国企改革、培育一批核心竞争力强的国有企业，一手抓促进民营经济发展壮大、激发各类经营主体活力。积极融入全国统一大市场建设，主动融入和服务国家重大战略，在推动共建“一带一路”、长江经济带、西部陆海新通道联动发展中发挥更大作用。主动对接高标准国际经贸规则，营造市场化法治化国际化一流营商环境。习近平指出，重庆是我国辖区面积和人口规模最大的城市，要深入践行人民城市理念，积极探索超大城市现代化治理新路子。加快智慧城市建设步伐，构建城市运行和治理智能中枢，建立健全“大综合一体化”城市综合治理体制机制，让城市治理更智能、更高效、更精准。扎实推进党建引领基层治理，坚持和发展新时代“枫桥经验”，深化城乡精神文明建设，推进移风易俗，提高全社会文明程度。全面推进韧性城市建设，有效提升防灾减灾救灾能力。习近平强调，重庆集大城市、大农村、大山区、大库区于一体，要大力推进城乡融合发展。积极推进以县（区）城为重要载体的新型城镇化建设，有序引导、依法规范城市工商资本和科技、人才下乡，助力乡村全面振兴。抓牢抓实粮食生产，依山就势发展生态特色农业。学好用好“千万工程”经验，因地制宜开展乡村建设，聚焦现阶段农民群众需求强烈、能抓得住、抓几年就能见到成效的重点实事，抓一件成一件，让农民群众可感可及、得到实惠。巩固拓展脱贫攻坚成果，确保不发生规模性返贫。习近平指出，要毫不放松坚持党的领导、加强党的建设。巩固拓展主题教育成果，建立健全长效机制，推动党员、干部特别是领导干部增强政治能力、提高工作水平，真抓实干、积极进取、担当作为。持续深化整治形式主义为基层减负，为基层干部干事创业创造良好条件。扎实开展党纪学习教育，引导党员、干部真正把纪律规矩转化为政治自觉、思想自觉、行动自觉。一以贯之反对和惩治腐败，不断铲除腐败滋生的土壤和条件，营造风清气正的政治生态。中共中央政治局常委、中央办公厅主任蔡奇陪同考察。李干杰、何立峰及中央和国家机关有关部门负责同志陪同考察。"
        },
        {
          "date": "20240424",
          "title": "【央视快评】奋力谱写西部大开发新篇章",
          "content": "本台今天（4月24日）播发央视快评《奋力谱写西部大开发新篇章》。"
        },
        {
          "date": "20240424",
          "title": "习近平向首届“中国－拉美和加勒比国家航天合作论坛”致贺信",
          "content": "4月24日，国家主席习近平向首届“中国－拉美和加勒比国家航天合作论坛”致贺信。习近平指出，今年是我同拉方领导人共同宣布成立中国－拉美和加勒比国家共同体论坛10周年。10年来，在中拉论坛框架内，中拉各领域友好合作蓬勃发展，推动中拉关系进入平等、互利、创新、开放、惠民的新时代。我高兴地看到，近年来，中拉航天合作结出丰硕果实。双方在遥感卫星、通信卫星和深空站网等领域合作不断取得新进展，为推动科技进步、加强区域互联、增进民生福祉发挥了重要作用。中国愿同拉美和加勒比国家一道，以首届中拉航天合作论坛为起点，建设高水平中拉航天合作伙伴关系，促进航天技术更好惠及双方人民，持续推动构建中拉命运共同体。首届“中国－拉美和加勒比国家航天合作论坛”当日在湖北武汉开幕，由中国国家航天局和湖北省人民政府共同主办。"
        },
        {
          "date": "20240424",
          "title": "李强在贵州调研",
          "content": "中共中央政治局常委、国务院总理李强4月24日在贵州调研。他强调，要深入贯彻习近平总书记关于巩固拓展脱贫攻坚成果的重要指示精神，毫不放松抓好各项政策和工作措施落实，拓宽农民增收致富渠道，持续增强内生发展动力，扎实有效巩固拓展脱贫攻坚成果，让脱贫群众生活一年更比一年好。凯里市白果井街道思源社区居住着近3000户易地搬迁群众。李强来到这里，听取安置点情况汇报，走进群众家中、就业帮扶车间询问搬迁群众就业、生活等状况。李强说，习近平总书记十分牵挂脱贫群众的生活，对巩固拓展脱贫攻坚成果作出了一系列重要指示。我们如期打赢脱贫攻坚战付出了艰苦努力，把脱贫攻坚成果巩固住、拓展好还需要接续奋斗。要保持帮扶工作力度，把各项政策衔接好、落到位，坚决守住不发生规模性返贫底线。要通过扩大本地就业岗位和加强异地就业服务相结合，让搬迁群众稳得住、有就业、能致富。在麻江县蓝梦谷生态蓝莓产业示范园，李强察看生产车间和产品展示，来到田间与种植人员交谈，了解全县蓝莓产业发展带动农旅融合情况。在台江县台拱街道红阳村，李强观看“村BA”直播，听取乡村体育产业、文旅产业发展情况汇报，走访脱贫群众。李强指出，要立足地域优势，发展休闲旅游、群众体育、民俗文化体验等，催生乡村经济新业态新亮点。要以品质树品牌，推动农业产业“接二连三”融合发展。要创新开展乡村文化体育活动，让农民群众既有更多收入又有丰富的精神文化生活。在台江县中等职业学校，李强察看茶艺、调酒实训室和非遗传承体验中心，了解校企合作及学生就业情况。李强指出，拥有一技之长、提升就业能力是脱贫致富的关键。要大力推进职业教育发展，用好东西部协作等机制，精准对接市场需求，培养更多技能型人才，让他们用自己掌握的本领，通过辛勤劳动创造美好生活。李强充分肯定贵州经济社会发展成就，希望贵州深入贯彻习近平总书记在新时代推动西部大开发座谈会上的重要讲话和关于贵州工作的重要指示精神，发挥优势，埋头苦干，为谱写西部大开发新篇章作出更大贡献。吴政隆陪同调研。"
        },
        {
          "date": "20240424",
          "title": "十四届全国人大常委会举行第二十四次委员长会议 听取有关草案和议案审议情况汇报 赵乐际主持",
          "content": "十四届全国人大常委会第二十四次委员长会议24日下午在北京人民大会堂举行。赵乐际委员长主持。会议听取了全国人大宪法和法律委员会主任委员信春鹰作的关于学位法草案修改意见的汇报，关于关税法草案修改意见的汇报，关于农业技术推广法等3部法律的修正案草案审议结果的报告，审议了相关草案修改稿、决定草案。会议听取了全国人大外事委员会主任委员娄勤俭作的关于《中华人民共和国和毛里求斯共和国关于刑事司法协助的条约》《中华人民共和国和尼泊尔关于刑事司法协助的条约》《中华人民共和国和塞内加尔共和国引渡条约》《中华人民共和国和希腊共和国引渡条约》审议情况的汇报，审议了关于批准条约的决定草案代拟稿。会议听取了全国人大常委会秘书长刘奇作的关于个别代表的代表资格的报告和任免案审议情况的汇报。委员长会议决定，将上述草案修改稿等提交常委会会议审议。"
        },
        {
          "date": "20240424",
          "title": "赵乐际在墨西哥参议院成立200周年庆祝活动上发表视频致辞",
          "content": "应墨西哥参议长里维拉邀请，全国人大常委会委员长赵乐际于墨西哥当地时间23日在墨参议院成立200周年庆祝活动上发表视频致辞。赵乐际在致辞中代表中国全国人大向墨西哥参议院成立200周年致以热烈祝贺。他表示，中墨建交50多年来，政治互信日益深化，务实合作成果丰硕。去年11月，习近平主席与洛佩斯总统成功会晤，为两国关系发展提供战略引领，为双边合作擘画蓝图。中方愿同墨方一道，加强战略对接，挖掘合作潜力，丰富中墨全面战略伙伴关系内涵。赵乐际指出，中国全国人大同墨西哥联邦议会一直保持友好交往，自2010年起已经举办了5届中墨立法机构对话论坛。希望两国立法机构深化多层次、多领域交流交往，加强立法、监督等方面经验交流，为互利合作提供法律支持，夯实中墨友好的社会和民意基础。赵乐际表示，墨西哥在拉美地区和全球具有重要影响力。中方愿同包括墨西哥在内的拉美国家加强多边协作，推动中墨、中拉关系行稳致远。"
        },
        {
          "date": "20240424",
          "title": "王沪宁会见哈萨克斯坦议会下院议长",
          "content": "全国政协主席王沪宁24日在京会见哈萨克斯坦议会下院议长科沙诺夫。王沪宁表示，在习近平主席和托卡耶夫总统的战略引领下，两国以高质量共建“一带一路”为主线，携手构建更加紧密的中哈命运共同体。中方愿同哈方一道，以两国元首重要共识为指引，坚定相互支持，推进务实合作，增进人民友好，丰富中哈永久全面战略伙伴关系内涵。中国全国政协愿为此作出积极贡献。科沙诺夫表示，中国拥有悠久灿烂的文明。在两国元首引领推动下，哈中命运共同体建设不断深化。祝贺中华人民共和国成立75周年。哈坚定支持中国的核心利益和重大关切。哈议会愿为促进哈中永久全面战略伙伴关系、增进人民之间的友好感情发挥积极作用。石泰峰、胡春华、王东峰等参加会见。"
        },
        {
          "date": "20240424",
          "title": "韩正会见哈萨克斯坦议会下院议长",
          "content": "国家副主席韩正24日在京会见哈萨克斯坦议会下院议长科沙诺夫。韩正表示，去年，习近平主席同托卡耶夫总统两度会晤，就构建中哈命运共同体作出了新部署。中哈关系已经开启新的“黄金三十年”，中方愿同哈方一道，落实好两国元首重要共识，在涉及彼此核心利益和重大关切问题上坚定相互支持；深化共建“一带一路”同哈新经济政策对接，充分发挥中哈合作委员会统筹协调作用，加强重点领域合作，深化人文交流；密切多边协作，推进落实全球发展倡议、全球安全倡议和全球文明倡议，共同践行真正的多边主义。科沙诺夫表示，今年是哈中建交32周年。哈中关系已升级为永久全面战略伙伴关系。哈方愿加强同中方务实合作，深化人民友谊，推进两国关系不断发展。"
        },
        {
          "date": "20240424",
          "title": "神舟十八号载人飞船发射窗口确定 航天员乘组亮相",
          "content": "今天（4月24日），神舟十八号载人飞行任务新闻发布会在酒泉卫星发射中心举行，计划于4月25日20时59分发射神舟十八号载人飞船，乘组三名航天员集体亮相。发布会上，中国载人航天工程新闻发言人介绍了此次任务的相关情况。中午11时，神舟十八号飞行乘组在问天阁与中外记者见面，乘组由航天员叶光富、李聪、李广苏组成。指令长叶光富执行过神舟十三号载人飞行任务，李聪和李广苏均为我国第三批航天员，都是首次执行飞行任务。正在空间站执行任务的神舟十七号乘组在轨观看神舟十八号载人飞行任务新闻发布会和记者见面会。目前，空间站组合体状态和各项设备工作正常，神舟十八号船箭组合体产品质量受控，地面系统设施设备运行稳定，发射前各项准备工作已就绪。"
        },
        {
          "date": "20240424",
          "title": "中央纪委国家监委公开通报八起违规吃喝典型问题",
          "content": "日前，中央纪委国家监委对八起违规吃喝典型问题进行公开通报。江西省人大常委会原党组副书记、副主任殷美根，生态环境部环境工程评估中心原党委委员、副主任邹世英，海南省旅游和文化广电体育厅二级巡视员刘平久，新疆生产建设兵团第六师副师长、五家渠市副市长闫盛红及兵团教育局党组成员、副局长尹若强，北京市财政局自然资源和生态环境处副处长裴阳，华电能源股份有限公司原党委委员、总会计师李西金，中国建设银行新疆维吾尔自治区博州分行党委委员、副行长吴建斌等人和云南省玉溪市新平彝族傣族自治县人民法院公款吃喝、接受可能影响公正执行公务的宴请等，受到严肃处理。中央纪委国家监委强调，各级党组织和领导干部要清醒认识违规吃喝问题的危害性，强化对本地区本单位本系统违规吃喝问题的研判，有针对性地开展整改整治。各级纪检监察机关要以高度责任感抓好违规吃喝整治，对顶风吃喝行为严惩不贷，对问题突出的地区、系统开展专项严查严处。要坚持一体推进“三不腐”，坚持党性党风党纪一起抓，建立健全长效治理机制。要坚守“五一”、端午节点，严肃纠治违规吃喝、违规收送礼品礼金、公款旅游等节日期间易发多发问题，及时通报典型案例，以有力有效举措，确保节日期间风清气正。"
        },
        {
          "date": "20240424",
          "title": "我国设立国家海外知识产权纠纷应对指导中心 为企业挽回经济损失68.9亿元",
          "content": "国务院新闻办公室今天（4月24日）举行发布会，国家知识产权局介绍，已经会同中国贸促会设立国家海外知识产权纠纷应对指导中心，并在27个省（区、市）布局建设了43家地方分中心，在贸易往来密集的国家和地区设立了工作指导站，为企业提供专业高效的海外维权指导服务。2023年，指导企业1706家，为企业挽回经济损失68.9亿元，帮助企业降低维权成本3.9亿元。"
        },
        {
          "date": "20240424",
          "title": "联播快讯",
          "content": "全国多地举行中国航天日活动今天（4月24日）是第九个中国航天日，以“极目楚天，共襄星汉”为主题的中国航天日主场活动在湖北武汉举行。活动现场，国家航天局发布了多项航天国际合作进展。在东风航天城，全国少工委组织各地的少先队员开展航天日主题活动。在北京航天城举办了以“征途向未来”为主题的航天科普展。在天津、江苏、云南等全国多地也举办了航天开放日、科普讲堂、知识竞赛等近500项丰富多彩的活动。1.1亿元中央自然灾害救灾资金支持赣粤桂防汛救灾近日，财政部、应急管理部紧急预拨1.1亿元中央自然灾害救灾资金，支持江西、广东、广西三省（区）防汛救灾工作，重点做好搜救转移安置受灾人员、排危除险等应急处置，开展次生灾害隐患排查和应急整治、倒损民房修复等。2024年联合国中文日暨总台第四届海外影像节举行当地时间4月23日，由中央广播电视总台与联合国日内瓦办事处、中国常驻联合国日内瓦办事处和瑞士其他国际组织代表团共同主办的2024年联合国中文日暨总台第四届海外影像节在联合国日内瓦办事处万国宫举行。本次活动以“青春与共：为推动构建人类命运共同体贡献青春力量”为主题，用语言和影像搭建起沟通的桥梁。以军与巴武装组织相互打击对方目标据以色列国防军23日发布的消息，以军对加沙地带中部、北部等多地进行数十次空袭，打击哈马斯目标。巴武装人员继续向以色列发射火箭弹。同一天，外媒公布了拉法和汗尤尼斯附近的前后对比卫星图像。报道称，对比图像显示这一区域新建了一批白色帐篷。以色列媒体就此报道称，埃及方面在以军对拉法实施地面行动前设立了该帐篷营地。印尼选委会正式宣布普拉博沃当选总统印度尼西亚选举委员会今天（4月24日）正式宣布普拉博沃当选为印尼第八任总统。普拉博沃将于10月20日就任总统。普拉博沃今天发表讲话说，新一届政府将致力于满足人民需求，努力消除贫困，为印尼带来繁荣，为人民带来福祉。"
        }
      ]
    },
    "百度财经": {
      "名称": "百度财经",
      "状态": "跳过",
      "错误": "云端获取百度 Cookie 403，已临时跳过",
      "数据": []
    },
    "百度研报时效": {
      "名称": "百度研报时效",
      "状态": "跳过",
      "错误": "云端获取百度 Cookie 403，已临时跳过",
      "数据": []
    },
    "财新要闻": {
      "名称": "财新要闻",
      "状态": "异常",
      "错误": "API Error: API request failed. Status code: 404 (Status code: None)",
      "堆栈": "Traceback (most recent call last):\n  File \"/home/runner/work/hana_helper/hana_helper/fetch_akshare.py\", line 29, in safe_fetch\n    df = fn()\n         ^^^^\n  File \"/home/runner/work/hana_helper/hana_helper/fetch_akshare.py\", line 55, in <lambda>\n    return safe_fetch(label, lambda: getattr(ak, attr)(*args, **kwargs))\n                                     ^^^^^^^^^^^^^^^^^^^^^^^^^^^^^^^^^^\n  File \"/opt/hostedtoolcache/Python/3.11.14/x64/lib/python3.11/site-packages/akshare/stock/stock_news_cx.py\", line 27, in stock_news_main_cx\n    data_json = make_request_with_retry_json(url, params=params)\n                ^^^^^^^^^^^^^^^^^^^^^^^^^^^^^^^^^^^^^^^^^^^^^^^^\n  File \"/opt/hostedtoolcache/Python/3.11.14/x64/lib/python3.11/site-packages/akshare/request.py\", line 44, in make_request_with_retry_json\n    raise APIError(\nakshare.exceptions.APIError: API Error: API request failed. Status code: 404 (Status code: None)\n",
      "数据": []
    }
  }
}